<keymap version="1" name="Default for XWin copy" parent="Default for XWin">
  <action id="$LRU">
    <keyboard-shortcut first-keystroke="alt f2" />
  </action>
  <action id="ActivateDebugToolWindow">
    <keyboard-shortcut first-keystroke="alt 5" />
    <keyboard-shortcut first-keystroke="alt left_parenthesis" />
  </action>
  <action id="ActivateFavoritesToolWindow">
    <keyboard-shortcut first-keystroke="alt 2" />
    <keyboard-shortcut first-keystroke="alt #10000e9" />
  </action>
  <action id="ActivateMavenProjectsToolWindow">
    <keyboard-shortcut first-keystroke="alt #10000e0" />
  </action>
  <action id="ActivateProjectToolWindow">
    <keyboard-shortcut first-keystroke="alt 1" />
    <keyboard-shortcut first-keystroke="alt ampersand" />
  </action>
  <action id="ActivateRunToolWindow">
    <keyboard-shortcut first-keystroke="alt 4" />
    <keyboard-shortcut first-keystroke="alt quote" />
  </action>
  <action id="ActivateStructureToolWindow">
    <keyboard-shortcut first-keystroke="alt 7" />
    <keyboard-shortcut first-keystroke="alt #10000e8" />
  </action>
  <action id="ActivateTODOToolWindow">
    <keyboard-shortcut first-keystroke="alt 6" />
    <keyboard-shortcut first-keystroke="alt minus" />
  </action>
  <action id="ActivateVersionControlToolWindow">
    <keyboard-shortcut first-keystroke="alt 9" />
    <keyboard-shortcut first-keystroke="alt #10000c7" />
  </action>
  <action id="CommentByBlockComment">
    <keyboard-shortcut first-keystroke="shift ctrl slash" />
    <keyboard-shortcut first-keystroke="shift ctrl divide" />
    <keyboard-shortcut first-keystroke="shift ctrl colon" />
  </action>
  <action id="CommentByLineComment">
    <keyboard-shortcut first-keystroke="ctrl slash" />
    <keyboard-shortcut first-keystroke="ctrl divide" />
    <keyboard-shortcut first-keystroke="ctrl colon" />
  </action>
  <action id="Editor LRU">
    <keyboard-shortcut first-keystroke="alt f2" />
  </action>
  <action id="Scala.ShowImplicits">
    <keyboard-shortcut first-keystroke="shift ctrl alt equals" />
    <keyboard-shortcut first-keystroke="shift ctrl alt add" />
  </action>
  <action id="SwitchApply">
    <keyboard-shortcut first-keystroke="shift alt enter" />
  </action>
  <action id="SwitchDown">
    <keyboard-shortcut first-keystroke="shift alt down" />
  </action>
  <action id="SwitchLeft">
    <keyboard-shortcut first-keystroke="shift alt left" />
  </action>
  <action id="SwitchRight">
    <keyboard-shortcut first-keystroke="shift alt right" />
  </action>
  <action id="SwitchUp">
    <keyboard-shortcut first-keystroke="shift alt up" />
  </action>
  <action id="Upsource.CreateOrShowDiscussion">
    <keyboard-shortcut first-keystroke="ctrl alt slash" />
    <keyboard-shortcut first-keystroke="ctrl alt colon" />
  </action>
</keymap>